hikrobotcamlib/__init__.py
hikrobotcamlib/console.py
hikrobotcamlib/errors.py
hikrobotcamlib/helpers.py
hikrobotcamlib/hiklibs/CameraParams_const.py
hikrobotcamlib/hiklibs/CameraParams_header.py
hikrobotcamlib/hiklibs/MvCameraControl_class.py
hikrobotcamlib/hiklibs/MvCameraControl_header.py
hikrobotcamlib/hiklibs/MvErrorDefine_const.py
hikrobotcamlib/hiklibs/PixelType_const.py
hikrobotcamlib/hiklibs/PixelType_header.py
hikrobotcamlib/hiklibs/__init__.py
hikrobotcamlib/py.typed
hikrobotcamlib/types.py
hikrobotcamlib/wrapper.py
hikrobotcamlib-1.2.0.dist-info/METADATA
hikrobotcamlib-1.2.0.dist-info/WHEEL
hikrobotcamlib-1.2.0.dist-info/entry_points.txt
hikrobotcamlib-1.2.0.dist-info/RECORD
