Metadata-Version: 2.1
Name: hikrobotcamlib
Version: 1.2.0
Summary: Package HIK Robotics camera drivers and some helpers
Home-page: https://gitlab.com/advian-oss/python-hikrobotcamlib/
License: MIT
Author: Eero af Heurlin
Author-email: eero.afheurlin@iki.fi
Requires-Python: >=3.8,<4.0
Classifier: License :: OSI Approved :: MIT License
Classifier: Programming Language :: Python :: 3
Classifier: Programming Language :: Python :: 3.8
Classifier: Programming Language :: Python :: 3.9
Classifier: Programming Language :: Python :: 3.10
Classifier: Programming Language :: Python :: 3.11
Classifier: Programming Language :: Python :: 3.12
Requires-Dist: click (>=8.0,<9.0)
Requires-Dist: libadvian (>=1.0,<2.0)
Project-URL: Repository, https://gitlab.com/advian-oss/python-hikrobotcamlib/
